solgraphPlus/__init__.py
solgraphPlus/main.py
solgraphPlus-0.0.5.dist-info/LICENSE
solgraphPlus-0.0.5.dist-info/METADATA
solgraphPlus-0.0.5.dist-info/WHEEL
solgraphPlus-0.0.5.dist-info/top_level.txt
solgraphPlus-0.0.5.dist-info/RECORD
